[{"pair_code":"ETH/ARS","prices":[{"pair_code":"ETH/ARS","price":"594500.00","name":"ripio"},{"pair_code":"ETH/ARS","price":"598052","name":"cryptomkt"},{"pair_code":"ETH/ARS","price":"602428.22","name":"criptoya"},{"pair_code":"ETH/ARS","price":"602550.0","name":"buda"},{"pair_code":"ETH/ARS","price":"607934.64","name":"bitso"},{"pair_code":"ETH/ARS","price":"608728.","name":"criptoya"},{"pair_code":"ETH/ARS","price":"613113.","name":"criptoya"},{"pair_code":"ETH/ARS","price":"617055.55","name":"criptoya"},{"pair_code":"ETH/ARS","price":"626870.97","name":"criptoya"}],"price":{"pair_code":"ETH/ARS","price":"607934.64","name":"bitso"}},{"pair_code":"BTC/ARS","prices":[{"pair_code":"BTC/ARS","price":"7887368","name":"cryptomkt"},{"pair_code":"BTC/ARS","price":"7.94100498e+06","name":"criptoya"},{"pair_code":"BTC/ARS","price":"7974999.91","name":"ripio"},{"pair_code":"BTC/ARS","price":"8022889.87","name":"bitso"},{"pair_code":"BTC/ARS","price":"8.03409595e+06","name":"criptoya"},{"pair_code":"BTC/ARS","price":"8040000.0","name":"buda"},{"pair_code":"BTC/ARS","price":"8.05803157e+06","name":"criptoya"},{"pair_code":"BTC/ARS","price":"8.084499e+06","name":"criptoya"},{"pair_code":"BTC/ARS","price":"8.15354464e+06","name":"criptoya"},{"pair_code":"BTC/ARS","price":"8.26124281e+06","name":"criptoya"}],"price":{"pair_code":"BTC/ARS","price":"8.03409595e+06","name":"criptoya"}},{"pair_code":"USDT/ARS","prices":[{"pair_code":"USDT/ARS","price":"189.0815","name":"criptoya"},{"pair_code":"USDT/ARS","price":"190.57","name":"criptoya"},{"pair_code":"USDT/ARS","price":"189.7883","name":"criptoya"},{"pair_code":"USDT/ARS","price":"192.198","name":"criptoya"},{"pair_code":"USDT/ARS","price":"192.3524","name":"criptoya"},{"pair_code":"USDT/ARS","price":"193.4235","name":"criptoya"}],"price":{"pair_code":"USDT/ARS","price":"189.7883","name":"criptoya"}},{"pair_code":"DAI/ARS","prices":[{"pair_code":"DAI/ARS","price":"188.80","name":"bitso"},{"pair_code":"DAI/ARS","price":"188.80","name":"ripio"},{"pair_code":"DAI/ARS","price":"188.9929","name":"criptoya"},{"pair_code":"DAI/ARS","price":"189.0312","name":"criptoya"},{"pair_code":"DAI/ARS","price":"190.51","name":"criptoya"},{"pair_code":"DAI/ARS","price":"193.2448","name":"criptoya"},{"pair_code":"DAI/ARS","price":"192.7314","name":"criptoya"},{"pair_code":"DAI/ARS","price":"192.6645","name":"criptoya"}],"price":{"pair_code":"DAI/ARS","price":"189.0312","name":"criptoya"}},{"pair_code":"USDC/ARS","prices":[{"pair_code":"USDC/ARS","price":"186.46","name":"ripio"},{"pair_code":"USDC/ARS","price":"188.88","name":"criptoya"},{"pair_code":"USDC/ARS","price":"189.8832","name":"criptoya"},{"pair_code":"USDC/ARS","price":"189.0761","name":"criptoya"},{"pair_code":"USDC/ARS","price":"191.0","name":"buda"},{"pair_code":"USDC/ARS","price":"190.44","name":"criptoya"},{"pair_code":"USDC/ARS","price":"193.4235","name":"criptoya"}],"price":{"pair_code":"USDC/ARS","price":"189.0761","name":"criptoya"}},{"pair_code":"ETH/BTC","prices":[{"pair_code":"ETH/BTC","price":"0.07582100","name":"binance"},{"pair_code":"ETH/BTC","price":"0.07582604","name":"bitso"},{"pair_code":"ETH/BTC","price":"0.0755","name":"buda"},{"pair_code":"ETH/BTC","price":"0.07578","name":"coinbase"},{"pair_code":"ETH/BTC","price":"0.07582","name":"crypto.com"},{"pair_code":"ETH/BTC","price":"0.075823","name":"cryptomkt"},{"pair_code":"ETH/BTC","price":"0.0758175","name":"ftx"},{"pair_code":"ETH/BTC","price":"0.075857","name":"gate.io"},{"pair_code":"ETH/BTC","price":"0.075822","name":"huobi"},{"pair_code":"ETH/BTC","price":"0.07581","name":"kucoin"},{"pair_code":"ETH/BTC","price":"0.088000","name":"ripio"},{"pair_code":"ETH/BTC","price":"0.07581","name":"okx"}],"price":{"pair_code":"ETH/BTC","price":"0.075823","name":"cryptomkt"}},{"pair_code":"BTC/DAI","prices":[{"pair_code":"BTC/DAI","price":"8201.800000","name":"ripio"},{"pair_code":"BTC/DAI","price":"42434.16000000","name":"binance"},{"pair_code":"BTC/DAI","price":"42435","name":"okx"},{"pair_code":"BTC/DAI","price":"42434.1","name":"kucoin"},{"pair_code":"BTC/DAI","price":"42439.94","name":"cryptomkt"},{"pair_code":"BTC/DAI","price":"42951.75","name":"bitso"}],"price":{"pair_code":"BTC/DAI","price":"42435","name":"okx"}},{"pair_code":"BTC/USDT","prices":[{"pair_code":"BTC/USDT","price":"42418.4","name":"kucoin"},{"pair_code":"BTC/USDT","price":"42420.22","name":"cryptomkt"},{"pair_code":"BTC/USDT","price":"42423.81","name":"huobi"},{"pair_code":"BTC/USDT","price":"42426.","name":"ftx"},{"pair_code":"BTC/USDT","price":"42426.5","name":"okx"},{"pair_code":"BTC/USDT","price":"42430.77","name":"crypto.com"},{"pair_code":"BTC/USDT","price":"42430.00000000","name":"binance"},{"pair_code":"BTC/USDT","price":"42432.96","name":"gate.io"},{"pair_code":"BTC/USDT","price":"42437.47","name":"coinbase"},{"pair_code":"BTC/USDT","price":"42445.92","name":"bitso"}],"price":{"pair_code":"BTC/USDT","price":"42426.5","name":"okx"}},{"pair_code":"BTC/USDC","prices":[{"pair_code":"BTC/USDC","price":"42418.2","name":"kucoin"},{"pair_code":"BTC/USDC","price":"42423.52042","name":"cryptomkt"},{"pair_code":"BTC/USDC","price":"42423.6","name":"okx"},{"pair_code":"BTC/USDC","price":"42425.44000000","name":"binance"},{"pair_code":"BTC/USDC","price":"42433.21","name":"huobi"},{"pair_code":"BTC/USDC","price":"42433.9","name":"coinbase"},{"pair_code":"BTC/USDC","price":"42437.49","name":"crypto.com"},{"pair_code":"BTC/USDC","price":"42500.0","name":"buda"},{"pair_code":"BTC/USDC","price":"43500.000000","name":"ripio"}],"price":{"pair_code":"BTC/USDC","price":"42433.21","name":"huobi"}},{"pair_code":"ETH/DAI","prices":[{"pair_code":"ETH/DAI","price":"210.140000","name":"ripio"},{"pair_code":"ETH/DAI","price":"3203.9","name":"kucoin"},{"pair_code":"ETH/DAI","price":"3216.42000000","name":"binance"},{"pair_code":"ETH/DAI","price":"3217.75","name":"coinbase"},{"pair_code":"ETH/DAI","price":"3218.614","name":"cryptomkt"},{"pair_code":"ETH/DAI","price":"3218.05","name":"okx"}],"price":{"pair_code":"ETH/DAI","price":"3216.42000000","name":"binance"}},{"pair_code":"ETH/USDT","prices":[{"pair_code":"ETH/USDT","price":"3217.21000000","name":"binance"},{"pair_code":"ETH/USDT","price":"3217.16","name":"coinbase"},{"pair_code":"ETH/USDT","price":"3217.39","name":"crypto.com"},{"pair_code":"ETH/USDT","price":"3217.126","name":"cryptomkt"},{"pair_code":"ETH/USDT","price":"3217.3","name":"ftx"},{"pair_code":"ETH/USDT","price":"3216.34","name":"kucoin"},{"pair_code":"ETH/USDT","price":"3217.03","name":"huobi"},{"pair_code":"ETH/USDT","price":"3217.42","name":"gate.io"},{"pair_code":"ETH/USDT","price":"3217.23","name":"okx"}],"price":{"pair_code":"ETH/USDT","price":"3217.3","name":"ftx"}},{"pair_code":"ETH/USDC","prices":[{"pair_code":"ETH/USDC","price":"3216.04000000","name":"binance"},{"pair_code":"ETH/USDC","price":"3216.61","name":"okx"},{"pair_code":"ETH/USDC","price":"3218","name":"coinbase"},{"pair_code":"ETH/USDC","price":"3217.243885","name":"cryptomkt"},{"pair_code":"ETH/USDC","price":"3217.78","name":"crypto.com"},{"pair_code":"ETH/USDC","price":"3218.51","name":"huobi"},{"pair_code":"ETH/USDC","price":"3217.84","name":"kucoin"},{"pair_code":"ETH/USDC","price":"3220.000000","name":"ripio"}],"price":{"pair_code":"ETH/USDC","price":"3217.243885","name":"cryptomkt"}},{"pair_code":"DAI/USDT","prices":[{"pair_code":"DAI/USDT","price":"1.01890000","name":"binance"},{"pair_code":"DAI/USDT","price":"0.9999","name":"crypto.com"},{"pair_code":"DAI/USDT","price":"0.9997","name":"ftx"},{"pair_code":"DAI/USDT","price":"0.9986","name":"gate.io"},{"pair_code":"DAI/USDT","price":"0.9997","name":"huobi"},{"pair_code":"DAI/USDT","price":"0.9997","name":"okx"}],"price":{"pair_code":"DAI/USDT","price":"0.9997","name":"ftx"}},{"pair_code":"DAI/USDC","prices":[{"pair_code":"DAI/USDC","price":"0.999965","name":"coinbase"},{"pair_code":"DAI/USDC","price":"1.0001","name":"crypto.com"},{"pair_code":"DAI/USDC","price":"1.00002750","name":"cryptomkt"}],"price":{"pair_code":"DAI/USDC","price":"1.0001","name":"crypto.com"}},{"pair_code":"USDC/USDT","prices":[{"pair_code":"USDC/USDT","price":"0.99990000","name":"binance"},{"pair_code":"USDC/USDT","price":"1.","name":"crypto.com"},{"pair_code":"USDC/USDT","price":"0.9999","name":"huobi"},{"pair_code":"USDC/USDT","price":"0.99984","name":"kucoin"},{"pair_code":"USDC/USDT","price":"1","name":"okx"}],"price":{"pair_code":"USDC/USDT","price":"0.9999","name":"huobi"}}]