[{"pair_code":"ETH/ARS","prices":[{"pair_code":"ETH/ARS","price":"590000.00","name":"ripio"},{"pair_code":"ETH/ARS","price":"610050.0","name":"buda"},{"pair_code":"ETH/ARS","price":"618384.","name":"criptoya"},{"pair_code":"ETH/ARS","price":"618978.53","name":"criptoya"},{"pair_code":"ETH/ARS","price":"620510.20","name":"bitso"},{"pair_code":"ETH/ARS","price":"623302.35","name":"criptoya"},{"pair_code":"ETH/ARS","price":"625401.15","name":"criptoya"},{"pair_code":"ETH/ARS","price":"627904.99","name":"criptoya"},{"pair_code":"ETH/ARS","price":"627904","name":"cryptomkt"}],"price":{"pair_code":"ETH/ARS","price":"620510.20","name":"bitso"}},{"pair_code":"BTC/ARS","prices":[{"pair_code":"BTC/ARS","price":"8.25167513e+06","name":"criptoya"},{"pair_code":"BTC/ARS","price":"8252000.00","name":"ripio"},{"pair_code":"BTC/ARS","price":"8.322076e+06","name":"criptoya"},{"pair_code":"BTC/ARS","price":"8344353.64","name":"bitso"},{"pair_code":"BTC/ARS","price":"8.344408e+06","name":"criptoya"},{"pair_code":"BTC/ARS","price":"8362995.95","name":"buda"},{"pair_code":"BTC/ARS","price":"8.3816453e+06","name":"criptoya"},{"pair_code":"BTC/ARS","price":"8394053","name":"cryptomkt"},{"pair_code":"BTC/ARS","price":"8.45502699e+06","name":"criptoya"},{"pair_code":"BTC/ARS","price":"8.50638917e+06","name":"criptoya"}],"price":{"pair_code":"BTC/ARS","price":"8.344408e+06","name":"criptoya"}},{"pair_code":"USDT/ARS","prices":[{"pair_code":"USDT/ARS","price":"188.3943","name":"criptoya"},{"pair_code":"USDT/ARS","price":"190","name":"criptoya"},{"pair_code":"USDT/ARS","price":"191.3225","name":"criptoya"},{"pair_code":"USDT/ARS","price":"192.8696","name":"criptoya"},{"pair_code":"USDT/ARS","price":"193.741","name":"criptoya"},{"pair_code":"USDT/ARS","price":"195.0206","name":"criptoya"}],"price":{"pair_code":"USDT/ARS","price":"191.3225","name":"criptoya"}},{"pair_code":"DAI/ARS","prices":[{"pair_code":"DAI/ARS","price":"184.07","name":"ripio"},{"pair_code":"DAI/ARS","price":"189.97","name":"criptoya"},{"pair_code":"DAI/ARS","price":"191.2967","name":"criptoya"},{"pair_code":"DAI/ARS","price":"190.75","name":"bitso"},{"pair_code":"DAI/ARS","price":"190.7589","name":"criptoya"},{"pair_code":"DAI/ARS","price":"191.7869","name":"criptoya"},{"pair_code":"DAI/ARS","price":"193.1745","name":"criptoya"},{"pair_code":"DAI/ARS","price":"195.179","name":"criptoya"}],"price":{"pair_code":"DAI/ARS","price":"190.75","name":"bitso"}},{"pair_code":"USDC/ARS","prices":[{"pair_code":"USDC/ARS","price":"180.1","name":"buda"},{"pair_code":"USDC/ARS","price":"183.94","name":"ripio"},{"pair_code":"USDC/ARS","price":"188.545","name":"criptoya"},{"pair_code":"USDC/ARS","price":"190.89","name":"criptoya"},{"pair_code":"USDC/ARS","price":"190.1","name":"criptoya"},{"pair_code":"USDC/ARS","price":"193.1789","name":"criptoya"},{"pair_code":"USDC/ARS","price":"195.0605","name":"criptoya"}],"price":{"pair_code":"USDC/ARS","price":"190.89","name":"criptoya"}},{"pair_code":"ETH/BTC","prices":[{"pair_code":"ETH/BTC","price":"0.07430100","name":"binance"},{"pair_code":"ETH/BTC","price":"0.07440000","name":"bitso"},{"pair_code":"ETH/BTC","price":"0.07449698","name":"buda"},{"pair_code":"ETH/BTC","price":"0.07429","name":"coinbase"},{"pair_code":"ETH/BTC","price":"0.074304","name":"crypto.com"},{"pair_code":"ETH/BTC","price":"0.074294","name":"cryptomkt"},{"pair_code":"ETH/BTC","price":"0.074315","name":"ftx"},{"pair_code":"ETH/BTC","price":"0.074355","name":"gate.io"},{"pair_code":"ETH/BTC","price":"0.07431","name":"huobi"},{"pair_code":"ETH/BTC","price":"0.074307","name":"kucoin"},{"pair_code":"ETH/BTC","price":"0.088400","name":"ripio"},{"pair_code":"ETH/BTC","price":"0.07429","name":"okx"}],"price":{"pair_code":"ETH/BTC","price":"0.074294","name":"cryptomkt"}},{"pair_code":"BTC/DAI","prices":[{"pair_code":"BTC/DAI","price":"8201.800000","name":"ripio"},{"pair_code":"BTC/DAI","price":"43701.2","name":"kucoin"},{"pair_code":"BTC/DAI","price":"43776.94","name":"cryptomkt"},{"pair_code":"BTC/DAI","price":"43776.4","name":"okx"},{"pair_code":"BTC/DAI","price":"43795.79000000","name":"binance"},{"pair_code":"BTC/DAI","price":"43965.90","name":"bitso"}],"price":{"pair_code":"BTC/DAI","price":"43776.94","name":"cryptomkt"}},{"pair_code":"BTC/USDT","prices":[{"pair_code":"BTC/USDT","price":"43775.30","name":"cryptomkt"},{"pair_code":"BTC/USDT","price":"43777.69","name":"crypto.com"},{"pair_code":"BTC/USDT","price":"43783.08","name":"gate.io"},{"pair_code":"BTC/USDT","price":"43786.31000000","name":"binance"},{"pair_code":"BTC/USDT","price":"43786.7","name":"kucoin"},{"pair_code":"BTC/USDT","price":"43785.9","name":"okx"},{"pair_code":"BTC/USDT","price":"43786.03","name":"huobi"},{"pair_code":"BTC/USDT","price":"43788.","name":"ftx"},{"pair_code":"BTC/USDT","price":"43791.32","name":"coinbase"},{"pair_code":"BTC/USDT","price":"43807.36","name":"bitso"}],"price":{"pair_code":"BTC/USDT","price":"43786.7","name":"kucoin"}},{"pair_code":"BTC/USDC","prices":[{"pair_code":"BTC/USDC","price":"43000.0","name":"buda"},{"pair_code":"BTC/USDC","price":"43743.56825","name":"cryptomkt"},{"pair_code":"BTC/USDC","price":"43783.01","name":"crypto.com"},{"pair_code":"BTC/USDC","price":"43786.78000000","name":"binance"},{"pair_code":"BTC/USDC","price":"43787.7","name":"coinbase"},{"pair_code":"BTC/USDC","price":"43790","name":"kucoin"},{"pair_code":"BTC/USDC","price":"43795.7","name":"okx"},{"pair_code":"BTC/USDC","price":"43800.94","name":"huobi"},{"pair_code":"BTC/USDC","price":"44050.000000","name":"ripio"}],"price":{"pair_code":"BTC/USDC","price":"43787.7","name":"coinbase"}},{"pair_code":"ETH/DAI","prices":[{"pair_code":"ETH/DAI","price":"210.140000","name":"ripio"},{"pair_code":"ETH/DAI","price":"3251.99","name":"coinbase"},{"pair_code":"ETH/DAI","price":"3251.69","name":"okx"},{"pair_code":"ETH/DAI","price":"3254.31000000","name":"binance"},{"pair_code":"ETH/DAI","price":"3253.954","name":"cryptomkt"},{"pair_code":"ETH/DAI","price":"3260.09","name":"kucoin"}],"price":{"pair_code":"ETH/DAI","price":"3251.69","name":"okx"}},{"pair_code":"ETH/USDT","prices":[{"pair_code":"ETH/USDT","price":"3249.35","name":"coinbase"},{"pair_code":"ETH/USDT","price":"3253.00000000","name":"binance"},{"pair_code":"ETH/USDT","price":"3253.06","name":"crypto.com"},{"pair_code":"ETH/USDT","price":"3252.897","name":"cryptomkt"},{"pair_code":"ETH/USDT","price":"3253.1","name":"ftx"},{"pair_code":"ETH/USDT","price":"3252.18","name":"gate.io"},{"pair_code":"ETH/USDT","price":"3253.34","name":"huobi"},{"pair_code":"ETH/USDT","price":"3253.53","name":"kucoin"},{"pair_code":"ETH/USDT","price":"3253.44","name":"okx"}],"price":{"pair_code":"ETH/USDT","price":"3253.1","name":"ftx"}},{"pair_code":"ETH/USDC","prices":[{"pair_code":"ETH/USDC","price":"3249.48","name":"kucoin"},{"pair_code":"ETH/USDC","price":"3250.845280","name":"cryptomkt"},{"pair_code":"ETH/USDC","price":"3252.61","name":"okx"},{"pair_code":"ETH/USDC","price":"3253.7","name":"coinbase"},{"pair_code":"ETH/USDC","price":"3253.87000000","name":"binance"},{"pair_code":"ETH/USDC","price":"3253.92","name":"crypto.com"},{"pair_code":"ETH/USDC","price":"3254.1","name":"huobi"},{"pair_code":"ETH/USDC","price":"3300.000000","name":"ripio"}],"price":{"pair_code":"ETH/USDC","price":"3253.7","name":"coinbase"}},{"pair_code":"DAI/USDT","prices":[{"pair_code":"DAI/USDT","price":"1.01890000","name":"binance"},{"pair_code":"DAI/USDT","price":"0.9999","name":"crypto.com"},{"pair_code":"DAI/USDT","price":"0.9997","name":"ftx"},{"pair_code":"DAI/USDT","price":"0.9988","name":"gate.io"},{"pair_code":"DAI/USDT","price":"0.9995","name":"huobi"}],"price":{"pair_code":"DAI/USDT","price":"0.9997","name":"ftx"}},{"pair_code":"DAI/USDC","prices":[{"pair_code":"DAI/USDC","price":"0.999984","name":"coinbase"},{"pair_code":"DAI/USDC","price":"1.","name":"crypto.com"},{"pair_code":"DAI/USDC","price":"0.99991356","name":"cryptomkt"}],"price":{"pair_code":"DAI/USDC","price":"1.","name":"crypto.com"}},{"pair_code":"USDC/USDT","prices":[{"pair_code":"USDC/USDT","price":"0.99990000","name":"binance"},{"pair_code":"USDC/USDT","price":"1.","name":"crypto.com"},{"pair_code":"USDC/USDT","price":"1.","name":"huobi"},{"pair_code":"USDC/USDT","price":"0.99983","name":"kucoin"}],"price":{"pair_code":"USDC/USDT","price":"1.","name":"crypto.com"}}]