[{"pair_code":"ETH/ARS","prices":[{"pair_code":"ETH/ARS","price":"590000.00","name":"ripio"},{"pair_code":"ETH/ARS","price":"605572.","name":"criptoya"},{"pair_code":"ETH/ARS","price":"606667.81","name":"criptoya"},{"pair_code":"ETH/ARS","price":"606841","name":"cryptomkt"},{"pair_code":"ETH/ARS","price":"608800.67","name":"criptoya"},{"pair_code":"ETH/ARS","price":"609327.12","name":"bitso"},{"pair_code":"ETH/ARS","price":"611473.99","name":"criptoya"},{"pair_code":"ETH/ARS","price":"612600.0","name":"buda"},{"pair_code":"ETH/ARS","price":"622990.53","name":"criptoya"}],"price":{"pair_code":"ETH/ARS","price":"608800.67","name":"criptoya"}},{"pair_code":"BTC/ARS","prices":[{"pair_code":"BTC/ARS","price":"7550000.23","name":"buda"},{"pair_code":"BTC/ARS","price":"8.15945293e+06","name":"criptoya"},{"pair_code":"BTC/ARS","price":"8.223451e+06","name":"criptoya"},{"pair_code":"BTC/ARS","price":"8252000.00","name":"ripio"},{"pair_code":"BTC/ARS","price":"8254516.13","name":"bitso"},{"pair_code":"BTC/ARS","price":"8.28311517e+06","name":"criptoya"},{"pair_code":"BTC/ARS","price":"8.28522599e+06","name":"criptoya"},{"pair_code":"BTC/ARS","price":"8294100","name":"cryptomkt"},{"pair_code":"BTC/ARS","price":"8.33147029e+06","name":"criptoya"},{"pair_code":"BTC/ARS","price":"8.46021706e+06","name":"criptoya"}],"price":{"pair_code":"BTC/ARS","price":"8254516.13","name":"bitso"}},{"pair_code":"USDT/ARS","prices":[{"pair_code":"USDT/ARS","price":"188.3943","name":"criptoya"},{"pair_code":"USDT/ARS","price":"190","name":"criptoya"},{"pair_code":"USDT/ARS","price":"191.3225","name":"criptoya"},{"pair_code":"USDT/ARS","price":"193.1784","name":"criptoya"},{"pair_code":"USDT/ARS","price":"193.46","name":"criptoya"},{"pair_code":"USDT/ARS","price":"193.754","name":"criptoya"}],"price":{"pair_code":"USDT/ARS","price":"191.3225","name":"criptoya"}},{"pair_code":"DAI/ARS","prices":[{"pair_code":"DAI/ARS","price":"184.07","name":"ripio"},{"pair_code":"DAI/ARS","price":"190.01","name":"criptoya"},{"pair_code":"DAI/ARS","price":"189.99","name":"bitso"},{"pair_code":"DAI/ARS","price":"189.99","name":"criptoya"},{"pair_code":"DAI/ARS","price":"191.7869","name":"criptoya"},{"pair_code":"DAI/ARS","price":"191.2967","name":"criptoya"},{"pair_code":"DAI/ARS","price":"193.1082","name":"criptoya"},{"pair_code":"DAI/ARS","price":"193.4564","name":"criptoya"}],"price":{"pair_code":"DAI/ARS","price":"189.99","name":"criptoya"}},{"pair_code":"USDC/ARS","prices":[{"pair_code":"USDC/ARS","price":"180.1","name":"buda"},{"pair_code":"USDC/ARS","price":"184.15","name":"ripio"},{"pair_code":"USDC/ARS","price":"188.5073","name":"criptoya"},{"pair_code":"USDC/ARS","price":"190.631","name":"criptoya"},{"pair_code":"USDC/ARS","price":"190.11","name":"criptoya"},{"pair_code":"USDC/ARS","price":"193.1784","name":"criptoya"},{"pair_code":"USDC/ARS","price":"193.5073","name":"criptoya"}],"price":{"pair_code":"USDC/ARS","price":"190.631","name":"criptoya"}},{"pair_code":"ETH/BTC","prices":[{"pair_code":"ETH/BTC","price":"0.07359100","name":"binance"},{"pair_code":"ETH/BTC","price":"0.07370000","name":"bitso"},{"pair_code":"ETH/BTC","price":"0.07449698","name":"buda"},{"pair_code":"ETH/BTC","price":"0.07364","name":"coinbase"},{"pair_code":"ETH/BTC","price":"0.073597","name":"crypto.com"},{"pair_code":"ETH/BTC","price":"0.073606","name":"cryptomkt"},{"pair_code":"ETH/BTC","price":"0.07361","name":"ftx"},{"pair_code":"ETH/BTC","price":"0.073645","name":"gate.io"},{"pair_code":"ETH/BTC","price":"0.073602","name":"huobi"},{"pair_code":"ETH/BTC","price":"0.073616","name":"kucoin"},{"pair_code":"ETH/BTC","price":"0.088400","name":"ripio"},{"pair_code":"ETH/BTC","price":"0.07361","name":"okx"}],"price":{"pair_code":"ETH/BTC","price":"0.073606","name":"cryptomkt"}},{"pair_code":"BTC/DAI","prices":[{"pair_code":"BTC/DAI","price":"8201.800000","name":"ripio"},{"pair_code":"BTC/DAI","price":"43253.5","name":"okx"},{"pair_code":"BTC/DAI","price":"43305.05","name":"cryptomkt"},{"pair_code":"BTC/DAI","price":"43321.09000000","name":"binance"},{"pair_code":"BTC/DAI","price":"43412.3","name":"kucoin"},{"pair_code":"BTC/DAI","price":"43790.72","name":"bitso"}],"price":{"pair_code":"BTC/DAI","price":"43305.05","name":"cryptomkt"}},{"pair_code":"BTC/USDT","prices":[{"pair_code":"BTC/USDT","price":"43305.58","name":"gate.io"},{"pair_code":"BTC/USDT","price":"43309.62","name":"huobi"},{"pair_code":"BTC/USDT","price":"43310","name":"ftx"},{"pair_code":"BTC/USDT","price":"43311.14","name":"cryptomkt"},{"pair_code":"BTC/USDT","price":"43310.77000000","name":"binance"},{"pair_code":"BTC/USDT","price":"43311.91","name":"crypto.com"},{"pair_code":"BTC/USDT","price":"43311","name":"okx"},{"pair_code":"BTC/USDT","price":"43312.54","name":"coinbase"},{"pair_code":"BTC/USDT","price":"43316.8","name":"kucoin"},{"pair_code":"BTC/USDT","price":"43334.04","name":"bitso"}],"price":{"pair_code":"BTC/USDT","price":"43310.77000000","name":"binance"}},{"pair_code":"BTC/USDC","prices":[{"pair_code":"BTC/USDC","price":"43000.0","name":"buda"},{"pair_code":"BTC/USDC","price":"43251.9","name":"kucoin"},{"pair_code":"BTC/USDC","price":"43307.93000","name":"cryptomkt"},{"pair_code":"BTC/USDC","price":"43310.8","name":"okx"},{"pair_code":"BTC/USDC","price":"43310.1","name":"coinbase"},{"pair_code":"BTC/USDC","price":"43315.51","name":"crypto.com"},{"pair_code":"BTC/USDC","price":"43317.76","name":"huobi"},{"pair_code":"BTC/USDC","price":"43329.63000000","name":"binance"},{"pair_code":"BTC/USDC","price":"44050.000000","name":"ripio"}],"price":{"pair_code":"BTC/USDC","price":"43310.1","name":"coinbase"}},{"pair_code":"ETH/DAI","prices":[{"pair_code":"ETH/DAI","price":"210.140000","name":"ripio"},{"pair_code":"ETH/DAI","price":"3183.410","name":"cryptomkt"},{"pair_code":"ETH/DAI","price":"3185.66","name":"okx"},{"pair_code":"ETH/DAI","price":"3188.57000000","name":"binance"},{"pair_code":"ETH/DAI","price":"3190.17","name":"coinbase"},{"pair_code":"ETH/DAI","price":"3193.48","name":"kucoin"}],"price":{"pair_code":"ETH/DAI","price":"3185.66","name":"okx"}},{"pair_code":"ETH/USDT","prices":[{"pair_code":"ETH/USDT","price":"3182.86","name":"coinbase"},{"pair_code":"ETH/USDT","price":"3186.170","name":"cryptomkt"},{"pair_code":"ETH/USDT","price":"3187.71","name":"crypto.com"},{"pair_code":"ETH/USDT","price":"3187.1","name":"ftx"},{"pair_code":"ETH/USDT","price":"3187.16","name":"gate.io"},{"pair_code":"ETH/USDT","price":"3187.21","name":"huobi"},{"pair_code":"ETH/USDT","price":"3187.46","name":"kucoin"},{"pair_code":"ETH/USDT","price":"3187.57","name":"okx"}],"price":{"pair_code":"ETH/USDT","price":"3187.1","name":"ftx"}},{"pair_code":"ETH/USDC","prices":[{"pair_code":"ETH/USDC","price":"3183.9","name":"coinbase"},{"pair_code":"ETH/USDC","price":"3185.02","name":"kucoin"},{"pair_code":"ETH/USDC","price":"3185.01","name":"okx"},{"pair_code":"ETH/USDC","price":"3185.313717","name":"cryptomkt"},{"pair_code":"ETH/USDC","price":"3188.15000000","name":"binance"},{"pair_code":"ETH/USDC","price":"3188.02","name":"crypto.com"},{"pair_code":"ETH/USDC","price":"3188.99","name":"huobi"},{"pair_code":"ETH/USDC","price":"3211.000000","name":"ripio"}],"price":{"pair_code":"ETH/USDC","price":"3185.313717","name":"cryptomkt"}},{"pair_code":"DAI/USDT","prices":[{"pair_code":"DAI/USDT","price":"1.01890000","name":"binance"},{"pair_code":"DAI/USDT","price":"0.9999","name":"crypto.com"},{"pair_code":"DAI/USDT","price":"1.","name":"ftx"},{"pair_code":"DAI/USDT","price":"0.9987","name":"gate.io"},{"pair_code":"DAI/USDT","price":"0.9997","name":"huobi"},{"pair_code":"DAI/USDT","price":"0.9999","name":"okx"}],"price":{"pair_code":"DAI/USDT","price":"1.","name":"ftx"}},{"pair_code":"DAI/USDC","prices":[{"pair_code":"DAI/USDC","price":"0.999799","name":"coinbase"},{"pair_code":"DAI/USDC","price":"1.","name":"crypto.com"},{"pair_code":"DAI/USDC","price":"0.99986869","name":"cryptomkt"}],"price":{"pair_code":"DAI/USDC","price":"1.","name":"crypto.com"}},{"pair_code":"USDC/USDT","prices":[{"pair_code":"USDC/USDT","price":"0.99990000","name":"binance"},{"pair_code":"USDC/USDT","price":"1.0001","name":"crypto.com"},{"pair_code":"USDC/USDT","price":"1.0001","name":"huobi"},{"pair_code":"USDC/USDT","price":"0.99979","name":"kucoin"},{"pair_code":"USDC/USDT","price":"1","name":"okx"}],"price":{"pair_code":"USDC/USDT","price":"1.0001","name":"huobi"}}]